HW2/decounter/decCounter.v
module decade_counter(
    //port declaration
    input clk,
    input rst,
    output [3:0] count,
    output ten
);
//register declaration
    reg [3:0] count;
    reg ten;

//logic
always @(posedge clk) 
begin
    if(rst == 1) 
    begin
        ten<=0;
        count<=4'b0000;
    end
    else 
    begin
        if(count <= 4'b1000)
        begin
            ten<=0;
            count<=count+4'b0001;
        end
        else
        begin
            ten<=1;
            count<=4'b0000;
        end
    end
end

endmodule

HW2/decounter/decCounter_tb.v
module decade_counter_tb();

reg clk;
reg rst;
wire [3:0]count;
wire ten;

decade_counter decade_counter_u0(
    .clk(clk),
    .rst(rst),
    .count(count),
    .ten(ten)
);

always 
begin
    #10 clk=!clk;
end

initial 
begin

    $dumpfile("decCounter.vcd");
    $dumpvars(0, decade_counter_tb);

    clk=0;rst=1;
    #40 rst=0;
    #290 rst=1;
    #40 rst=0;
    #290 $finish;

    
end

endmodule

HW2/decounter/decCounter.vcd
$date
	Thu Jan 25 19:31:57 2024
$end
$version
	Icarus Verilog
$end
$timescale
	1s
$end
$scope module decade_counter_tb $end
$var wire 1 ! ten $end
$var wire 4 " count [3:0] $end
$var reg 1 # clk $end
$var reg 1 $ rst $end
$scope module decade_counter_u0 $end
$var wire 1 # clk $end
$var wire 1 $ rst $end
$var reg 4 % count [3:0] $end
$var reg 1 ! ten $end
$upscope $end
$upscope $end
$enddefinitions $end
$comment Show the parameter values. $end
$dumpall
$end
#0
$dumpvars
bx %
1$
0#
bx "
x!
$end
#10
b0 "
b0 %
0!
1#
#20
0#
#30
1#
#40
0#
0$
#50
b1 "
b1 %
1#
#60
0#
#70
b10 "
b10 %
1#
#80
0#
#90
b11 "
b11 %
1#
#100
0#
#110
b100 "
b100 %
1#
#120
0#
#130
b101 "
b101 %
1#
#140
0#
#150
b110 "
b110 %
1#
#160
0#
#170
b111 "
b111 %
1#
#180
0#
#190
b1000 "
b1000 %
1#
#200
0#
#210
b1001 "
b1001 %
1#
#220
0#
#230
b0 "
b0 %
1!
1#
#240
0#
#250
b1 "
b1 %
0!
1#
#260
0#
#270
b10 "
b10 %
1#
#280
0#
#290
b11 "
b11 %
1#
#300
0#
#310
b100 "
b100 %
1#
#320
0#
#330
b0 "
b0 %
1#
1$
#340
0#
#350
1#
#360
0#
#370
b1 "
b1 %
1#
0$
#380
0#
#390
b10 "
b10 %
1#
#400
0#
#410
b11 "
b11 %
1#
#420
0#
#430
b100 "
b100 %
1#
#440
0#
#450
b101 "
b101 %
1#
#460
0#
#470
b110 "
b110 %
1#
#480
0#
#490
b111 "
b111 %
1#
#500
0#
#510
b1000 "
b1000 %
1#
#520
0#
#530
b1001 "
b1001 %
1#
#540
0#
#550
b0 "
b0 %
1!
1#
#560
0#
#570
b1 "
b1 %
0!
1#
#580
0#
#590
b10 "
b10 %
1#
#600
0#
#610
b11 "
b11 %
1#
#620
0#
#630
b100 "
b100 %
1#
#640
0#
#650
b101 "
b101 %
1#
