HW1/Norlatch/e1_norlatch.v
//nor latch
module nor_rs(q,qb,r,s);
    //port declaration
    output q,qb;
    input r,s;

    //logic
    nor #1 nr1(q,r,qb);
    nor #2 nr2(qb,q,s);
endmodule

HW1/Norlatch/norlatch_tb.v
//nor latch testbench
module nor_rs_tb;
    wire q,qb;
    reg s,r;

    nor_rs t1(q,qb,s,r);

initial
 begin
    //waveform
    $dumpfile("norlatch.vcd");
    $dumpvars(0, nor_rs_tb);

    //monitor
    $monitor("# %d  Input: s = $b , r = %b  Output: q = %b , qb = %b", $realtime,s,r,q,qb);

    //pattern
    s=1;r=0; 
    #10 s=0;r=0; 
    #10 s=0;r=1; 
    #10 s=0;r=0;
    #10 s=1;r=1;
    #10 $finish;
 end

endmodule

HW1/Norlatch/norlatch.vcd
$date
	Thu Jan 25 17:55:55 2024
$end
$version
	Icarus Verilog
$end
$timescale
	1s
$end
$scope module nor_rs_tb $end
$var wire 1 ! qb $end
$var wire 1 " q $end
$var reg 1 # r $end
$var reg 1 $ s $end
$scope module t1 $end
$var wire 1 " q $end
$var wire 1 ! qb $end
$var wire 1 $ r $end
$var wire 1 # s $end
$upscope $end
$upscope $end
$enddefinitions $end
$comment Show the parameter values. $end
$dumpall
$end
#0
$dumpvars
1$
0#
x"
x!
$end
#1
0"
#2
1!
#10
0$
#20
1#
#21
0!
#22
1"
#30
0#
#40
1#
1$
#41
0"
