HW2/NIBBLEADD/nibbleadd.v
//!DO NOT EDIT MODULE NAME AND PORT NAME!
module nibbleadd(
    input [7:0]A,
    input [7:0]B,
    input ctrl,
    output reg [4:0]q
);

always @ (A,B,ctrl) begin
    
    if(ctrl==1)
    begin
        q <= A[7:4]+B[7:4];
    end
    else
        q <= A[3:0]+B[3:0];
end

endmodule

HW2/NIBBLEADD/nibbleadd_tb.v
module nibbleadd_tb();

    reg [7:0]A;
    reg [7:0]B;
    reg ctrl;
    wire [4:0]q;

nibbleadd nibbleadd_t0(
    A,B,ctrl,q
);

initial 
begin

    $dumpfile("nibbleadd.vcd");
    $dumpvars(0, nibbleadd_tb);
    A=8'h24;B=8'h81;ctrl=0;
    #10 A=8'h09;B=8'h63;
    #10 A=8'h0d;B=8'h8d;
    #10 A=8'h65;B=8'h12;
    #10 A=8'h01;B=8'h0d;
    #10 A=8'h76;B=8'h3d;ctrl=1;
    #10 A=8'hed;B=8'h8c;
    #10 A=8'hf9;B=8'hc6;
    #10 A=8'hc5;B=8'haa;
    #10 A=8'he5;B=8'h77;
    #10 A=8'h12;B=8'h8f;
    #10 $finish;

end

endmodule

HW2/NIBBLEADD/nibbleadd.vcd
$date
	Thu Feb 08 15:08:10 2024
$end
$version
	Icarus Verilog
$end
$timescale
	1s
$end
$scope module nibbleadd_tb $end
$var wire 5 ! q [4:0] $end
$var reg 8 " A [7:0] $end
$var reg 8 # B [7:0] $end
$var reg 1 $ ctrl $end
$scope module nibbleadd_t0 $end
$var wire 8 % A [7:0] $end
$var wire 8 & B [7:0] $end
$var wire 1 $ ctrl $end
$var reg 5 ' q [4:0] $end
$upscope $end
$upscope $end
$enddefinitions $end
$comment Show the parameter values. $end
$dumpall
$end
#0
$dumpvars
b101 '
b10000001 &
b100100 %
0$
b10000001 #
b100100 "
b101 !
$end
#10
b1100 !
b1100 '
b1100011 #
b1100011 &
b1001 "
b1001 %
#20
b11010 !
b11010 '
b10001101 #
b10001101 &
b1101 "
b1101 %
#30
b111 !
b111 '
b10010 #
b10010 &
b1100101 "
b1100101 %
#40
b1110 !
b1110 '
b1101 #
b1101 &
b1 "
b1 %
#50
b1010 !
b1010 '
1$
b111101 #
b111101 &
b1110110 "
b1110110 %
#60
b10110 !
b10110 '
b10001100 #
b10001100 &
b11101101 "
b11101101 %
#70
b11011 !
b11011 '
b11000110 #
b11000110 &
b11111001 "
b11111001 %
#80
b10110 !
b10110 '
b10101010 #
b10101010 &
b11000101 "
b11000101 %
#90
b10101 !
b10101 '
b1110111 #
b1110111 &
b11100101 "
b11100101 %
#100
b1001 !
b1001 '
b10001111 #
b10001111 &
b10010 "
b10010 %
